factory_queue/__init__.py
factory_queue/core.py
factory_queue/factory.py
factory_queue/factory_queue.py
factory_queue-0.1.4.dist-info/licenses/LICENSE
factory_queue-0.1.4.dist-info/METADATA
factory_queue-0.1.4.dist-info/WHEEL
factory_queue-0.1.4.dist-info/top_level.txt
factory_queue-0.1.4.dist-info/RECORD
