Metadata-Version: 2.4
Name: factory-queue
Version: 0.1.4
Summary: 流水线工厂模块，支持多节点、多工位、资源控制、磁盘溢出
Home-page: https://github.com/yourusername/factory-queue
Author: Your Name
Author-email: Your Name <your.email@example.com>
License: MIT
Project-URL: Homepage, https://github.com/yourusername/factory-queue
Project-URL: Bug Reports, https://github.com/yourusername/factory-queue/issues
Project-URL: Source, https://github.com/yourusername/factory-queue
Keywords: pipeline,factory,queue,node,multi-threading,disk-overflow
Classifier: Development Status :: 3 - Alpha
Classifier: Intended Audience :: Developers
Classifier: Topic :: Software Development :: Libraries :: Python Modules
Classifier: License :: OSI Approved :: MIT License
Classifier: Programming Language :: Python :: 3
Classifier: Programming Language :: Python :: 3.7
Classifier: Programming Language :: Python :: 3.8
Classifier: Programming Language :: Python :: 3.9
Classifier: Programming Language :: Python :: 3.10
Classifier: Programming Language :: Python :: 3.11
Requires-Python: >=3.7
License-File: LICENSE
Requires-Dist: psutil>=5.8.0
Dynamic: author
Dynamic: home-page
Dynamic: license-file
Dynamic: requires-python
